reqtest/__init__.py
reqtest-0.0.1.dist-info/LICENSE
reqtest-0.0.1.dist-info/WHEEL
reqtest-0.0.1.dist-info/METADATA
reqtest-0.0.1.dist-info/RECORD
