Metadata-Version: 2.1
Name: reqtest
Version: 0.0.1
Summary: Automate everything HTTP.
Home-page: https://github.com/vcokltfre/reqtest
License: MIT
Keywords: reqtest,requests,http,automation,testing
Author: vcokltfre
Author-email: vcokltfre@gmail.com
Requires-Python: >=3.10,<4.0
Classifier: License :: OSI Approved :: MIT License
Classifier: Programming Language :: Python :: 3
Classifier: Programming Language :: Python :: 3.10
Project-URL: Repository, https://github.com/vcokltfre/reqtest
